[
  {
    "Vak": "Ak",
    "Afnamemoment": "TW1",
    "jaarlaag": "H4",
    "Omschrijving": "H2: Wereld: Wereldbeeld"
  },
  {
    "Vak": "Ak",
    "Afnamemoment": "TW2",
    "jaarlaag": "H4",
    "Omschrijving": "H3: Aarde: Klimaat en Landschap"
  },
  {
    "Vak": "Ak",
    "Afnamemoment": "TW3",
    "jaarlaag": "H4",
    "Omschrijving": "H1: Nederland wateroverlast"
  },
  {
    "Vak": "Ak",
    "Afnamemoment": "P4",
    "jaarlaag": "H4",
    "Omschrijving": "H1: Nederland wateroverlast"
  },
  {
    "Vak": "Ak",
    "Afnamemoment": "TW4",
    "jaarlaag": "H4",
    "Omschrijving": "H4: Leefomgeving stedelijke gebieden"
  },
  {
    "Vak": "Ak",
    "Afnamemoment": "TW1",
    "jaarlaag": "H5",
    "Omschrijving": "H4: Leefomgeving stedelijke gebieden"
  },
  {
    "Vak": "Ak",
    "Afnamemoment": "TW2",
    "jaarlaag": "H5",
    "Omschrijving": "H4: Leefomgeving stedelijke gebieden"
  },
  {
    "Vak": "Ak",
    "Afnamemoment": "TW3",
    "jaarlaag": "H5",
    "Omschrijving": "H4: Leefomgeving stedelijke gebieden"
  },
  {
    "Vak": "Beco",
    "Afnamemoment": "P1",
    "jaarlaag": "H4",
    "Omschrijving": "Begrippentoets Financiële zelfredzaamheid"
  },
  {
    "Vak": "Beco",
    "Afnamemoment": "TW1",
    "jaarlaag": "H4",
    "Omschrijving": "Financiële zelfredzaamheid"
  },
  {
    "Vak": "Beco",
    "Afnamemoment": "P2",
    "jaarlaag": "H4",
    "Omschrijving": "Begrippentoets Bedrijf starten"
  },
  {
    "Vak": "Beco",
    "Afnamemoment": "P2",
    "jaarlaag": "H4",
    "Omschrijving": "Bedrijf starten"
  },
  {
    "Vak": "Beco",
    "Afnamemoment": "P3",
    "jaarlaag": "H4",
    "Omschrijving": "Begrippentoets Marktverovering en Onderneem-het-zelf"
  },
  {
    "Vak": "Beco",
    "Afnamemoment": "TW3",
    "jaarlaag": "H4",
    "Omschrijving": "Bedrijf starten, Marktverovering, Onderneem-het-zelf"
  },
  {
    "Vak": "Beco",
    "Afnamemoment": "P4",
    "jaarlaag": "H4",
    "Omschrijving": "Marktverovering Onderneem-het-zelf"
  },
  {
    "Vak": "Beco",
    "Afnamemoment": "P4",
    "jaarlaag": "H4",
    "Omschrijving": "Marktverovering Onderneem-het-zelf"
  },
  {
    "Vak": "Beco",
    "Afnamemoment": "TW1",
    "jaarlaag": "H5",
    "Omschrijving": "Marktverovering Onderneem-het-zelf"
  },
  {
    "Vak": "Beco",
    "Afnamemoment": "TW2",
    "jaarlaag": "H5",
    "Omschrijving": "Marktverovering Onderneem-het-zelf"
  },
  {
    "Vak": "Beco",
    "Afnamemoment": "TW3",
    "jaarlaag": "H5",
    "Omschrijving": "Marktverovering Onderneem-het-zelf"
  },
  {
    "Vak": "Biol",
    "Afnamemoment": "TW1",
    "jaarlaag": "H4",
    "Omschrijving": "H2: Cellen - H3: Onderzoek doen"
  },
  {
    "Vak": "Biol",
    "Afnamemoment": "TW2",
    "jaarlaag": "H4",
    "Omschrijving": "H1: Gedrag - H4: Voortplanting & seksualiteit"
  },
  {
    "Vak": "Biol",
    "Afnamemoment": "P4",
    "jaarlaag": "H4",
    "Omschrijving": "Practicum toets"
  },
  {
    "Vak": "Biol",
    "Afnamemoment": "TW3",
    "jaarlaag": "H4",
    "Omschrijving": "H5: Voeding & Energie - H6: Voeding, vertering & gezondheid"
  },
  {
    "Vak": "Biol",
    "Afnamemoment": "TW4",
    "jaarlaag": "H4",
    "Omschrijving": "H7: Soorten & relaties - H8: Ecosysteem & evenwicht"
  },
  {
    "Vak": "Biol",
    "Afnamemoment": "TW1",
    "jaarlaag": "H5",
    "Omschrijving": "H7: Soorten & relaties - H8: Ecosysteem & evenwicht"
  },
  {
    "Vak": "Biol",
    "Afnamemoment": "TW2",
    "jaarlaag": "H5",
    "Omschrijving": "H7: Soorten & relaties - H8: Ecosysteem & evenwicht"
  },
  {
    "Vak": "Biol",
    "Afnamemoment": "TW3",
    "jaarlaag": "H5",
    "Omschrijving": "H7: Soorten & relaties - H8: Ecosysteem & evenwicht"
  },
  {
    "Vak": "Bsm",
    "Afnamemoment": "P1",
    "jaarlaag": "H4",
    "Omschrijving": "H7: Soorten & relaties - H8: Ecosysteem & evenwicht"
  },
  {
    "Vak": "Bsm",
    "Afnamemoment": "P1",
    "jaarlaag": "H4",
    "Omschrijving": "Lesgeven I: Groene Spelen"
  },
  {
    "Vak": "Bsm",
    "Afnamemoment": "P1",
    "jaarlaag": "H4",
    "Omschrijving": "Spel I"
  },
  {
    "Vak": "Bsm",
    "Afnamemoment": "P3",
    "jaarlaag": "H4",
    "Omschrijving": "Spel I"
  },
  {
    "Vak": "Bsm",
    "Afnamemoment": "P3",
    "jaarlaag": "H4",
    "Omschrijving": "Spel I"
  },
  {
    "Vak": "Bsm",
    "Afnamemoment": "TW1",
    "jaarlaag": "H4",
    "Omschrijving": "Toernooiopdracht + Organisatie van Sport en Bewegen en motieven in de sport"
  },
  {
    "Vak": "Bsm",
    "Afnamemoment": "P3",
    "jaarlaag": "H4",
    "Omschrijving": "Demo (Bom en Turnen I)"
  },
  {
    "Vak": "Bsm",
    "Afnamemoment": "TW2",
    "jaarlaag": "H4",
    "Omschrijving": "Blessurepreventie en behandeling"
  },
  {
    "Vak": "Bsm",
    "Afnamemoment": "P3",
    "jaarlaag": "H4",
    "Omschrijving": "Fitheidstests en Duurconditie"
  },
  {
    "Vak": "Bsm",
    "Afnamemoment": "P4",
    "jaarlaag": "H4",
    "Omschrijving": "Fitheidstests en Duurconditie"
  },
  {
    "Vak": "Bsm",
    "Afnamemoment": "P4",
    "jaarlaag": "H4",
    "Omschrijving": "Fitheidstests en Duurconditie"
  },
  {
    "Vak": "Bsm",
    "Afnamemoment": "TW3",
    "jaarlaag": "H4",
    "Omschrijving": "Energiesystemen en trainingsprincipes"
  },
  {
    "Vak": "Bsm",
    "Afnamemoment": "P4",
    "jaarlaag": "H4",
    "Omschrijving": "Atletiek"
  },
  {
    "Vak": "Bsm",
    "Afnamemoment": "P1",
    "jaarlaag": "H5",
    "Omschrijving": "Atletiek"
  },
  {
    "Vak": "Bsm",
    "Afnamemoment": "P1",
    "jaarlaag": "H5",
    "Omschrijving": "Zelfverdediging"
  },
  {
    "Vak": "Bsm",
    "Afnamemoment": "P2",
    "jaarlaag": "H5",
    "Omschrijving": "Zelfverdediging"
  },
  {
    "Vak": "Bsm",
    "Afnamemoment": "P3",
    "jaarlaag": "H5",
    "Omschrijving": "Zelfverdediging"
  },
  {
    "Vak": "Bsm",
    "Afnamemoment": "P3",
    "jaarlaag": "H5",
    "Omschrijving": "Zelfverdediging"
  },
  {
    "Vak": "Bsm",
    "Afnamemoment": "P3",
    "jaarlaag": "H5",
    "Omschrijving": "Turnen II"
  },
  {
    "Vak": "Bsm",
    "Afnamemoment": "TW2",
    "jaarlaag": "H5",
    "Omschrijving": "Turnen II"
  },
  {
    "Vak": "Bsm",
    "Afnamemoment": "P3",
    "jaarlaag": "H5",
    "Omschrijving": "Turnen II"
  },
  {
    "Vak": "Ckv",
    "Afnamemoment": "P1",
    "jaarlaag": "H4",
    "Omschrijving": "Cultureel zelfportret"
  },
  {
    "Vak": "Ckv",
    "Afnamemoment": "P1",
    "jaarlaag": "H4",
    "Omschrijving": "Feit en fictie"
  },
  {
    "Vak": "Ckv",
    "Afnamemoment": "P4",
    "jaarlaag": "H4",
    "Omschrijving": "Feit en fictie"
  },
  {
    "Vak": "Ckv",
    "Afnamemoment": "P2",
    "jaarlaag": "H4",
    "Omschrijving": "Groot onderzoek"
  },
  {
    "Vak": "Ckv",
    "Afnamemoment": "P3",
    "jaarlaag": "H4",
    "Omschrijving": "Culturele activiteit Amusement"
  },
  {
    "Vak": "Ckv",
    "Afnamemoment": "P3",
    "jaarlaag": "H4",
    "Omschrijving": "Lokaal en globaal"
  },
  {
    "Vak": "Ckv",
    "Afnamemoment": "P4",
    "jaarlaag": "H4",
    "Omschrijving": "Traditie en innovatie"
  },
  {
    "Vak": "Ckv",
    "Afnamemoment": "P4",
    "jaarlaag": "H4",
    "Omschrijving": "Reflectie"
  },
  {
    "Vak": "Dutl",
    "Afnamemoment": "TW1",
    "jaarlaag": "H4",
    "Omschrijving": "Grammatica"
  },
  {
    "Vak": "Dutl",
    "Afnamemoment": "P1",
    "jaarlaag": "H4",
    "Omschrijving": "idioom"
  },
  {
    "Vak": "Dutl",
    "Afnamemoment": "P2",
    "jaarlaag": "H4",
    "Omschrijving": "kijk- en luistertoets"
  },
  {
    "Vak": "Dutl",
    "Afnamemoment": "TW2",
    "jaarlaag": "H4",
    "Omschrijving": "persoonlijke brief"
  },
  {
    "Vak": "Dutl",
    "Afnamemoment": "TW3",
    "jaarlaag": "H4",
    "Omschrijving": "Tekstverklaring"
  },
  {
    "Vak": "Dutl",
    "Afnamemoment": "TW3",
    "jaarlaag": "H4",
    "Omschrijving": "mondeling"
  },
  {
    "Vak": "Dutl",
    "Afnamemoment": "P3",
    "jaarlaag": "H4",
    "Omschrijving": "idioom"
  },
  {
    "Vak": "Dutl",
    "Afnamemoment": "TW4",
    "jaarlaag": "H4",
    "Omschrijving": "Tekstverklaring"
  },
  {
    "Vak": "Dutl",
    "Afnamemoment": "Eind",
    "jaarlaag": "H4",
    "Omschrijving": "Gemiddelde huiswerktoetsen uit de periodes"
  },
  {
    "Vak": "Dutl",
    "Afnamemoment": "TW1",
    "jaarlaag": "H5",
    "Omschrijving": "Mondeling 25 15"
  },
  {
    "Vak": "Dutl",
    "Afnamemoment": "P1",
    "jaarlaag": "H5",
    "Omschrijving": "Mondeling 25 15"
  },
  {
    "Vak": "Dutl",
    "Afnamemoment": "TW2",
    "jaarlaag": "H5",
    "Omschrijving": "Mondeling 25 15"
  },
  {
    "Vak": "Dutl",
    "Afnamemoment": "P3",
    "jaarlaag": "H5",
    "Omschrijving": "Mondeling 25 15"
  },
  {
    "Vak": "Dutl",
    "Afnamemoment": "TW3",
    "jaarlaag": "H5",
    "Omschrijving": "Mondeling 25 15"
  },
  {
    "Vak": "Econ",
    "Afnamemoment": "TW1",
    "jaarlaag": "H4",
    "Omschrijving": "Rekonomie en Crisis"
  },
  {
    "Vak": "Econ",
    "Afnamemoment": "P2",
    "jaarlaag": "H4",
    "Omschrijving": "Rekonomie en Crisis"
  },
  {
    "Vak": "Econ",
    "Afnamemoment": "P2",
    "jaarlaag": "H4",
    "Omschrijving": "Begrippentoets Jong & Oud"
  },
  {
    "Vak": "Econ",
    "Afnamemoment": "TW2",
    "jaarlaag": "H4",
    "Omschrijving": "Jong & Oud"
  },
  {
    "Vak": "Econ",
    "Afnamemoment": "P3",
    "jaarlaag": "H4",
    "Omschrijving": "Jong & Oud"
  },
  {
    "Vak": "Econ",
    "Afnamemoment": "P3",
    "jaarlaag": "H4",
    "Omschrijving": "Begrippentoets Vragers & Aanbieders"
  },
  {
    "Vak": "Econ",
    "Afnamemoment": "TW3",
    "jaarlaag": "H4",
    "Omschrijving": "Vragers & Aanbieders"
  },
  {
    "Vak": "Econ",
    "Afnamemoment": "P4",
    "jaarlaag": "H4",
    "Omschrijving": "Begrippentoets Markt & Overheid"
  },
  {
    "Vak": "Econ",
    "Afnamemoment": "TW4",
    "jaarlaag": "H4",
    "Omschrijving": "Markt & Overheid"
  },
  {
    "Vak": "Econ",
    "Afnamemoment": "TW1",
    "jaarlaag": "H5",
    "Omschrijving": "Markt & Overheid"
  },
  {
    "Vak": "Econ",
    "Afnamemoment": "TW2",
    "jaarlaag": "H5",
    "Omschrijving": "Markt & Overheid"
  },
  {
    "Vak": "Econ",
    "Afnamemoment": "TW3",
    "jaarlaag": "H5",
    "Omschrijving": "Markt & Overheid"
  },
  {
    "Vak": "Entl",
    "Afnamemoment": "TW1",
    "jaarlaag": "H4",
    "Omschrijving": "Spreekvaardigheid speaking a.d.h.v. WASP"
  },
  {
    "Vak": "Entl",
    "Afnamemoment": "TW2",
    "jaarlaag": "H4",
    "Omschrijving": "Writing (schrijfopdracht a.d.h.v. stellingen/ opinion)"
  },
  {
    "Vak": "Entl",
    "Afnamemoment": "P4",
    "jaarlaag": "H4",
    "Omschrijving": "Literatuuropdracht"
  },
  {
    "Vak": "Entl",
    "Afnamemoment": "P4",
    "jaarlaag": "H4",
    "Omschrijving": "Luistervaardigheid"
  },
  {
    "Vak": "Entl",
    "Afnamemoment": "TW4",
    "jaarlaag": "H4",
    "Omschrijving": "Leesvaardigheid + leesstrategieën (signaalwoorden in P4 telt 30% mee voor VT45)"
  },
  {
    "Vak": "Entl",
    "Afnamemoment": "TW1",
    "jaarlaag": "H5",
    "Omschrijving": "Leesvaardigheid + leesstrategieën (signaalwoorden in P4 telt 30% mee voor VT45)"
  },
  {
    "Vak": "Entl",
    "Afnamemoment": "P2",
    "jaarlaag": "H5",
    "Omschrijving": "Leesvaardigheid + leesstrategieën (signaalwoorden in P4 telt 30% mee voor VT45)"
  },
  {
    "Vak": "Entl",
    "Afnamemoment": "TW2",
    "jaarlaag": "H5",
    "Omschrijving": "Leesvaardigheid + leesstrategieën (signaalwoorden in P4 telt 30% mee voor VT45)"
  },
  {
    "Vak": "Entl",
    "Afnamemoment": "P3",
    "jaarlaag": "H5",
    "Omschrijving": "Leesvaardigheid + leesstrategieën (signaalwoorden in P4 telt 30% mee voor VT45)"
  },
  {
    "Vak": "Entl",
    "Afnamemoment": "TW3",
    "jaarlaag": "H5",
    "Omschrijving": "Leesvaardigheid + leesstrategieën (signaalwoorden in P4 telt 30% mee voor VT45)"
  },
  {
    "Vak": "Fatl",
    "Afnamemoment": "P1",
    "jaarlaag": "H4",
    "Omschrijving": "Luistertoets ERK A2"
  },
  {
    "Vak": "Fatl",
    "Afnamemoment": "TW1",
    "jaarlaag": "H4",
    "Omschrijving": "TW1: Leestoets ERK A2+ en schrijftoets (schrijven over chapitre"
  },
  {
    "Vak": "Fatl",
    "Afnamemoment": "P2",
    "jaarlaag": "H4",
    "Omschrijving": "Luister en kijktoets ERK A2"
  },
  {
    "Vak": "Fatl",
    "Afnamemoment": "TW2",
    "jaarlaag": "H4",
    "Omschrijving": "TW2: Leestoets ERK A2+ en schrijftoets (schrijven over chapitre"
  },
  {
    "Vak": "Fatl",
    "Afnamemoment": "P3",
    "jaarlaag": "H4",
    "Omschrijving": "Kijk en luistertoets CITO"
  },
  {
    "Vak": "Fatl",
    "Afnamemoment": "TW3",
    "jaarlaag": "H4",
    "Omschrijving": "TW3: Leestoets ERK A2+ en schrijftoets (schrijven over chapitre"
  },
  {
    "Vak": "Fatl",
    "Afnamemoment": "P4",
    "jaarlaag": "H4",
    "Omschrijving": "Kennistoets basis woordenschat en basis grammatica"
  },
  {
    "Vak": "Fatl",
    "Afnamemoment": "TW4",
    "jaarlaag": "H4",
    "Omschrijving": "TW4: Spreek en gespreksvaardigheid"
  },
  {
    "Vak": "Fatl",
    "Afnamemoment": "TW1",
    "jaarlaag": "H5",
    "Omschrijving": "TW4: Spreek en gespreksvaardigheid"
  },
  {
    "Vak": "Fatl",
    "Afnamemoment": "TW2",
    "jaarlaag": "H5",
    "Omschrijving": "Mondeling 25 H 15"
  },
  {
    "Vak": "Fatl",
    "Afnamemoment": "P3",
    "jaarlaag": "H5",
    "Omschrijving": "Mondeling 25 H 15"
  },
  {
    "Vak": "Fatl",
    "Afnamemoment": "TW3",
    "jaarlaag": "H5",
    "Omschrijving": "Mondeling 25 H 15"
  },
  {
    "Vak": "Ges",
    "Afnamemoment": "TW1",
    "jaarlaag": "H4",
    "Omschrijving": "Tijdvak"
  },
  {
    "Vak": "Ges",
    "Afnamemoment": "P1",
    "jaarlaag": "H4",
    "Omschrijving": "Praktische oprdracht formuleren (schriftcijfer)"
  },
  {
    "Vak": "Ges",
    "Afnamemoment": "TW2",
    "jaarlaag": "H4",
    "Omschrijving": "Tijdvak 1, 2,"
  },
  {
    "Vak": "Ges",
    "Afnamemoment": "P3",
    "jaarlaag": "H4",
    "Omschrijving": "Thema Rijksmuseum"
  },
  {
    "Vak": "Ges",
    "Afnamemoment": "TW3",
    "jaarlaag": "H4",
    "Omschrijving": "Tijdvak"
  },
  {
    "Vak": "Ges",
    "Afnamemoment": "TW4",
    "jaarlaag": "H4",
    "Omschrijving": "Tijdvak"
  },
  {
    "Vak": "Ges",
    "Afnamemoment": "TW1",
    "jaarlaag": "H5",
    "Omschrijving": "Historische Context: Het Britse rijk en Tijdvak"
  },
  {
    "Vak": "Ges",
    "Afnamemoment": "TW2",
    "jaarlaag": "H5",
    "Omschrijving": "Historische context: Duitsland in Europa en Tijdvak"
  },
  {
    "Vak": "Ges",
    "Afnamemoment": "P3",
    "jaarlaag": "H5",
    "Omschrijving": "Thema lange termijn ontwikkelingen (kenmerkende aspectentoets)"
  },
  {
    "Vak": "Ges",
    "Afnamemoment": "TW3",
    "jaarlaag": "H5",
    "Omschrijving": "Historische context"
  },
  {
    "Vak": "In",
    "Afnamemoment": "TW1",
    "jaarlaag": "H4",
    "Omschrijving": "Historische context"
  },
  {
    "Vak": "In",
    "Afnamemoment": "P2",
    "jaarlaag": "H4",
    "Omschrijving": "HTML5, CSS3 en JavaScript +"
  },
  {
    "Vak": "In",
    "Afnamemoment": "TW3",
    "jaarlaag": "H4",
    "Omschrijving": "Security + Informatica in de samenleving"
  },
  {
    "Vak": "In",
    "Afnamemoment": "TW4",
    "jaarlaag": "H4",
    "Omschrijving": "Programmeren met Pyhton: Turtle / micro:bit / Olympiade"
  },
  {
    "Vak": "In",
    "Afnamemoment": "TW1",
    "jaarlaag": "H5",
    "Omschrijving": "Programmeren met Pyhton: Turtle / micro:bit / Olympiade"
  },
  {
    "Vak": "In",
    "Afnamemoment": "P2",
    "jaarlaag": "H5",
    "Omschrijving": "Programmeren met Pyhton: Turtle / micro:bit / Olympiade"
  },
  {
    "Vak": "In",
    "Afnamemoment": "P3",
    "jaarlaag": "H5",
    "Omschrijving": "Programmeren met Pyhton: Turtle / micro:bit / Olympiade"
  },
  {
    "Vak": "Lo",
    "Afnamemoment": "P1",
    "jaarlaag": "H4",
    "Omschrijving": "Programmeren met Pyhton: Turtle / micro:bit / Olympiade"
  },
  {
    "Vak": "Lo",
    "Afnamemoment": "P2",
    "jaarlaag": "H4",
    "Omschrijving": "Programmeren met Pyhton: Turtle / micro:bit / Olympiade"
  },
  {
    "Vak": "Lo",
    "Afnamemoment": "P3",
    "jaarlaag": "H4",
    "Omschrijving": "Programmeren met Pyhton: Turtle / micro:bit / Olympiade"
  },
  {
    "Vak": "Lo",
    "Afnamemoment": "P4",
    "jaarlaag": "H4",
    "Omschrijving": "Programmeren met Pyhton: Turtle / micro:bit / Olympiade"
  },
  {
    "Vak": "Lo",
    "Afnamemoment": "P1",
    "jaarlaag": "H5",
    "Omschrijving": "Programmeren met Pyhton: Turtle / micro:bit / Olympiade"
  },
  {
    "Vak": "Lo",
    "Afnamemoment": "P2",
    "jaarlaag": "H5",
    "Omschrijving": "Programmeren met Pyhton: Turtle / micro:bit / Olympiade"
  },
  {
    "Vak": "Maat",
    "Afnamemoment": "TW1",
    "jaarlaag": "H4",
    "Omschrijving": "H1 Wat is Maatschappijleer"
  },
  {
    "Vak": "Maat",
    "Afnamemoment": "P1",
    "jaarlaag": "H4",
    "Omschrijving": "Sociale Actualiteit Analyse"
  },
  {
    "Vak": "Maat",
    "Afnamemoment": "TW2",
    "jaarlaag": "H4",
    "Omschrijving": "H3 Parlementaire Democratie"
  },
  {
    "Vak": "Maat",
    "Afnamemoment": "TW3",
    "jaarlaag": "H4",
    "Omschrijving": "H2 Rechtsstaat"
  },
  {
    "Vak": "Maat",
    "Afnamemoment": "TW4",
    "jaarlaag": "H4",
    "Omschrijving": "H5 Verzorgingsstaat en H4 Pluriforme samenleving"
  },
  {
    "Vak": "Maat",
    "Afnamemoment": "P4",
    "jaarlaag": "H4",
    "Omschrijving": "Herhaling H2 Rechtsstaat en H3 Parlementaire democratie - Praktische Opdracht"
  },
  {
    "Vak": "Maw",
    "Afnamemoment": "P1",
    "jaarlaag": "H4",
    "Omschrijving": "Inleiding MAW, H1 Vorming - Analyse Sociale Actualiteit"
  },
  {
    "Vak": "Maw",
    "Afnamemoment": "TW1",
    "jaarlaag": "H4",
    "Omschrijving": "H1 Vorming en H2 Binding"
  },
  {
    "Vak": "Maw",
    "Afnamemoment": "TW2",
    "jaarlaag": "H4",
    "Omschrijving": "H3 Verhouding, H4 Verandering"
  },
  {
    "Vak": "Maw",
    "Afnamemoment": "P3",
    "jaarlaag": "H4",
    "Omschrijving": "H5 Onderzoeksvaardigheden - Onderzoek Politieke Actualiteit"
  },
  {
    "Vak": "Maw",
    "Afnamemoment": "TW3",
    "jaarlaag": "H4",
    "Omschrijving": "H6 Binding en Verandering, H7 Vorming en Verandering"
  },
  {
    "Vak": "Maw",
    "Afnamemoment": "TW4",
    "jaarlaag": "H4",
    "Omschrijving": "H8 Verhouding, H9 Veiligheid"
  },
  {
    "Vak": "Maw",
    "Afnamemoment": "TW1",
    "jaarlaag": "H5",
    "Omschrijving": "H8 Verhouding, H9 Veiligheid"
  },
  {
    "Vak": "Maw",
    "Afnamemoment": "P2",
    "jaarlaag": "H5",
    "Omschrijving": "H8 Verhouding, H9 Veiligheid"
  },
  {
    "Vak": "Maw",
    "Afnamemoment": "TW2",
    "jaarlaag": "H5",
    "Omschrijving": "H8 Verhouding, H9 Veiligheid"
  },
  {
    "Vak": "Maw",
    "Afnamemoment": "P3",
    "jaarlaag": "H5",
    "Omschrijving": "Reproductie Hoofd- en Kernconcepten"
  },
  {
    "Vak": "Maw",
    "Afnamemoment": "P3",
    "jaarlaag": "H5",
    "Omschrijving": "Redeneren met Hoofd- en Kernconcepten"
  },
  {
    "Vak": "Maw",
    "Afnamemoment": "TW3",
    "jaarlaag": "H5",
    "Omschrijving": "Redeneren met Hoofd- en Kernconcepten"
  },
  {
    "Vak": "Mu",
    "Afnamemoment": "P1",
    "jaarlaag": "H4",
    "Omschrijving": "Koorwerk"
  },
  {
    "Vak": "Mu",
    "Afnamemoment": "TW1",
    "jaarlaag": "H4",
    "Omschrijving": "Musicbox"
  },
  {
    "Vak": "Mu",
    "Afnamemoment": "P2",
    "jaarlaag": "H4",
    "Omschrijving": "Ensemblestuk uitvoeren"
  },
  {
    "Vak": "Mu",
    "Afnamemoment": "TW2",
    "jaarlaag": "H4",
    "Omschrijving": "Musicbox"
  },
  {
    "Vak": "Mu",
    "Afnamemoment": "P3",
    "jaarlaag": "H4",
    "Omschrijving": "Singer-songwriter (solo)"
  },
  {
    "Vak": "Mu",
    "Afnamemoment": "TW3",
    "jaarlaag": "H4",
    "Omschrijving": "Observatie en reflectie SE Havo"
  },
  {
    "Vak": "Mu",
    "Afnamemoment": "TW3",
    "jaarlaag": "H4",
    "Omschrijving": "Musicbox"
  },
  {
    "Vak": "Mu",
    "Afnamemoment": "P4",
    "jaarlaag": "H4",
    "Omschrijving": "Eigen band compositie inleveren en uitvoeren"
  },
  {
    "Vak": "Mu",
    "Afnamemoment": "TW4",
    "jaarlaag": "H4",
    "Omschrijving": "Musicbox"
  },
  {
    "Vak": "Mu",
    "Afnamemoment": "P1",
    "jaarlaag": "H5",
    "Omschrijving": "A prima vista spelen en improviseren 10 10"
  },
  {
    "Vak": "Mu",
    "Afnamemoment": "TW1",
    "jaarlaag": "H5",
    "Omschrijving": "A prima vista spelen en improviseren 10 10"
  },
  {
    "Vak": "Mu",
    "Afnamemoment": "TW2",
    "jaarlaag": "H5",
    "Omschrijving": "A prima vista spelen en improviseren 10 10"
  },
  {
    "Vak": "Mu",
    "Afnamemoment": "P3",
    "jaarlaag": "H5",
    "Omschrijving": "A prima vista spelen en improviseren 10 10"
  },
  {
    "Vak": "Nat",
    "Afnamemoment": "P4",
    "jaarlaag": "H4",
    "Omschrijving": "Optica"
  },
  {
    "Vak": "Nat",
    "Afnamemoment": "TW1",
    "jaarlaag": "H4",
    "Omschrijving": "H1 Beweging"
  },
  {
    "Vak": "Nat",
    "Afnamemoment": "TW2",
    "jaarlaag": "H4",
    "Omschrijving": "H1 Beweging en H2 Elektriciteit"
  },
  {
    "Vak": "Nat",
    "Afnamemoment": "TW3",
    "jaarlaag": "H4",
    "Omschrijving": "H2 Elektriciteit en H3 krachten"
  },
  {
    "Vak": "Nat",
    "Afnamemoment": "TW4",
    "jaarlaag": "H4",
    "Omschrijving": "H1 Beweging, H2 Elektriciteit en H3 Krachten"
  },
  {
    "Vak": "Nat",
    "Afnamemoment": "P4",
    "jaarlaag": "H4",
    "Omschrijving": "Practicum"
  },
  {
    "Vak": "Nat",
    "Afnamemoment": "TW1",
    "jaarlaag": "H5",
    "Omschrijving": "Practicum"
  },
  {
    "Vak": "Nat",
    "Afnamemoment": "TW2",
    "jaarlaag": "H5",
    "Omschrijving": "Practicum"
  },
  {
    "Vak": "Nat",
    "Afnamemoment": "TW3",
    "jaarlaag": "H5",
    "Omschrijving": "Practicum"
  },
  {
    "Vak": "Nat",
    "Afnamemoment": "P2",
    "jaarlaag": "H5",
    "Omschrijving": "Technische automatisering"
  },
  {
    "Vak": "Nat",
    "Afnamemoment": "P3",
    "jaarlaag": "H5",
    "Omschrijving": "Practium"
  },
  {
    "Vak": "Netl",
    "Afnamemoment": "TW1",
    "jaarlaag": "H4",
    "Omschrijving": "Literatuur en Literatuurgeschiedenis"
  },
  {
    "Vak": "Netl",
    "Afnamemoment": "TW2",
    "jaarlaag": "H4",
    "Omschrijving": "Argumenteren en Formuleren"
  },
  {
    "Vak": "Netl",
    "Afnamemoment": "TW3",
    "jaarlaag": "H4",
    "Omschrijving": "Schrijfvaardigheid: zakelijke brief"
  },
  {
    "Vak": "Netl",
    "Afnamemoment": "P4",
    "jaarlaag": "H4",
    "Omschrijving": "Presentatie"
  },
  {
    "Vak": "Netl",
    "Afnamemoment": "TW4",
    "jaarlaag": "H4",
    "Omschrijving": "Leesvaardigheid: Lezen / complexe teksten"
  },
  {
    "Vak": "Netl",
    "Afnamemoment": "TW1",
    "jaarlaag": "H5",
    "Omschrijving": "Leesvaardigheid: Lezen / complexe teksten"
  },
  {
    "Vak": "Netl",
    "Afnamemoment": "TW2",
    "jaarlaag": "H5",
    "Omschrijving": "Leesvaardigheid: Lezen / complexe teksten"
  },
  {
    "Vak": "Netl",
    "Afnamemoment": "P3",
    "jaarlaag": "H5",
    "Omschrijving": "Mondeling Betoog in tweetallen 25 15"
  },
  {
    "Vak": "Netl",
    "Afnamemoment": "TW3",
    "jaarlaag": "H5",
    "Omschrijving": "Mondeling Betoog in tweetallen 25 15"
  },
  {
    "Vak": "Re",
    "Afnamemoment": "P2",
    "jaarlaag": "H4",
    "Omschrijving": "Rekentoets: getallen, verhoudingen, meetkunde en verbanden."
  },
  {
    "Vak": "Schk",
    "Afnamemoment": "TW1",
    "jaarlaag": "H4",
    "Omschrijving": "H01: Scheiden en reageren - H02: Bouwstenen van stoffen"
  },
  {
    "Vak": "Schk",
    "Afnamemoment": "TW2",
    "jaarlaag": "H4",
    "Omschrijving": "H03: Stoffen en reacties - H04: Moleculaire stoffen"
  },
  {
    "Vak": "Schk",
    "Afnamemoment": "P3",
    "jaarlaag": "H4",
    "Omschrijving": "Practicum inclusief verslag - H2, H4, H5"
  },
  {
    "Vak": "Schk",
    "Afnamemoment": "TW4",
    "jaarlaag": "H4",
    "Omschrijving": "Practicum inclusief verslag - H2, H4, H5"
  },
  {
    "Vak": "Schk",
    "Afnamemoment": "TW1",
    "jaarlaag": "H5",
    "Omschrijving": "Practicum inclusief verslag - H2, H4, H5"
  },
  {
    "Vak": "Schk",
    "Afnamemoment": "P2",
    "jaarlaag": "H5",
    "Omschrijving": "Practicum inclusief verslag - H2, H4, H5"
  },
  {
    "Vak": "Schk",
    "Afnamemoment": "TW3",
    "jaarlaag": "H5",
    "Omschrijving": "Practicum inclusief verslag - H2, H4, H5"
  },
  {
    "Vak": "Te",
    "Afnamemoment": "P1",
    "jaarlaag": "H4",
    "Omschrijving": "De boom"
  },
  {
    "Vak": "Te",
    "Afnamemoment": "TW1",
    "jaarlaag": "H4",
    "Omschrijving": "Klassieke oudheid en middeleeuwen"
  },
  {
    "Vak": "Te",
    "Afnamemoment": "P2",
    "jaarlaag": "H4",
    "Omschrijving": "Griekse kop en modeltekenen"
  },
  {
    "Vak": "Te",
    "Afnamemoment": "TW2",
    "jaarlaag": "H4",
    "Omschrijving": "Renaissance, barok, neo-classicisme"
  },
  {
    "Vak": "Te",
    "Afnamemoment": "P3",
    "jaarlaag": "H4",
    "Omschrijving": "Fotografie"
  },
  {
    "Vak": "Te",
    "Afnamemoment": "TW3",
    "jaarlaag": "H4",
    "Omschrijving": "Negentiende eeuw"
  },
  {
    "Vak": "Te",
    "Afnamemoment": "P4",
    "jaarlaag": "H4",
    "Omschrijving": "Keuzeopdracht"
  },
  {
    "Vak": "Te",
    "Afnamemoment": "TW4",
    "jaarlaag": "H4",
    "Omschrijving": "Modernisme"
  },
  {
    "Vak": "Te",
    "Afnamemoment": "P1",
    "jaarlaag": "H5",
    "Omschrijving": "Modernisme"
  },
  {
    "Vak": "Te",
    "Afnamemoment": "TW1",
    "jaarlaag": "H5",
    "Omschrijving": "Modernisme"
  },
  {
    "Vak": "Te",
    "Afnamemoment": "P2",
    "jaarlaag": "H5",
    "Omschrijving": "Modernisme"
  },
  {
    "Vak": "Te",
    "Afnamemoment": "TW2",
    "jaarlaag": "H5",
    "Omschrijving": "Eindexamen stof i.c.m. thema"
  },
  {
    "Vak": "Te",
    "Afnamemoment": "P3",
    "jaarlaag": "H5",
    "Omschrijving": "Eindexamen stof i.c.m. thema"
  },
  {
    "Vak": "Te",
    "Afnamemoment": "TW3",
    "jaarlaag": "H5",
    "Omschrijving": "Eindexamen stof i.c.m. thema"
  },
  {
    "Vak": "Wds",
    "Afnamemoment": "TW2",
    "jaarlaag": "H4",
    "Omschrijving": "A Deel 1: Hoofdstuk"
  },
  {
    "Vak": "Wds",
    "Afnamemoment": "TW4",
    "jaarlaag": "H4",
    "Omschrijving": "A Deel 1: Hoofdstuk"
  },
  {
    "Vak": "Wisa",
    "Afnamemoment": "P1",
    "jaarlaag": "H4",
    "Omschrijving": "Deel 1: Hoofdstuk"
  },
  {
    "Vak": "Wisa",
    "Afnamemoment": "TW1",
    "jaarlaag": "H4",
    "Omschrijving": "Deel 1: Hoofdstuk"
  },
  {
    "Vak": "Wisa",
    "Afnamemoment": "TW2",
    "jaarlaag": "H4",
    "Omschrijving": "Deel 1: Hoofdstuk"
  },
  {
    "Vak": "Wisa",
    "Afnamemoment": "TW3",
    "jaarlaag": "H4",
    "Omschrijving": "Deel 1: Hoofdstuk"
  },
  {
    "Vak": "Wisa",
    "Afnamemoment": "P4",
    "jaarlaag": "H4",
    "Omschrijving": "Deel 1: Hoofdstuk"
  },
  {
    "Vak": "Wisa",
    "Afnamemoment": "TW1",
    "jaarlaag": "H5",
    "Omschrijving": "Deel 3: Hoofdstuk"
  },
  {
    "Vak": "Wisa",
    "Afnamemoment": "TW2",
    "jaarlaag": "H5",
    "Omschrijving": "Deel 2: Hoofdstuk"
  },
  {
    "Vak": "Wisa",
    "Afnamemoment": "TW3",
    "jaarlaag": "H5",
    "Omschrijving": "Deel 2: Hoofdstuk"
  },
  {
    "Vak": "Wisb",
    "Afnamemoment": "P1",
    "jaarlaag": "H4",
    "Omschrijving": "Deel 1: Hoofdstuk"
  },
  {
    "Vak": "Wisb",
    "Afnamemoment": "TW1",
    "jaarlaag": "H4",
    "Omschrijving": "Deel 1: Hoofdstuk"
  },
  {
    "Vak": "Wisb",
    "Afnamemoment": "TW2",
    "jaarlaag": "H4",
    "Omschrijving": "Deel 1: Hoofdstuk 2,"
  },
  {
    "Vak": "Wisb",
    "Afnamemoment": "TW3",
    "jaarlaag": "H4",
    "Omschrijving": "Deel 1: Hoofdstuk"
  },
  {
    "Vak": "Wisb",
    "Afnamemoment": "TW4",
    "jaarlaag": "H4",
    "Omschrijving": "Deel 2: Hoofdstuk 5,"
  },
  {
    "Vak": "Wisb",
    "Afnamemoment": "TW1",
    "jaarlaag": "H5",
    "Omschrijving": "Deel 2: Hoofdstuk"
  },
  {
    "Vak": "Wisb",
    "Afnamemoment": "TW2",
    "jaarlaag": "H5",
    "Omschrijving": "Deel 3: Hoofdstuk"
  },
  {
    "Vak": "Wisb",
    "Afnamemoment": "TW3",
    "jaarlaag": "H5",
    "Omschrijving": "Deel 1: Hoofdstuk"
  }
]